[
  {
    "id": "2411240000040",
    "name": "三重県厚生農業協同組合連合会　三重北医療センターいなべ総合病院",
    "tel": "2411240000040",
    "url": "http://www.miekosei.or.jp/4_ish/index.html",
    "address": "三重県いなべ市北勢町阿下喜７７１",
    "pref": "三重県",
    "city": "いなべ市北勢町阿下喜",
    "kind": "hospital",
    "departments": [
      "内科",
      "脳神経内科",
      "外科",
      "脳神経外科",
      "整形外科",
      "小児科",
      "産婦人科",
      "眼科",
      "耳鼻いんこう科",
      "皮膚科",
      "泌尿器科"
    ]
  },
  {
    "id": "2411240000210",
    "name": "日下病院",
    "tel": "2411240000210",
    "url": "http://www.kusaka-hp.jp",
    "address": "三重県いなべ市北勢町阿下喜６８０",
    "pref": "三重県",
    "city": "いなべ市北勢町阿下喜",
    "kind": "hospital",
    "departments": [
      "内科",
      "糖尿病内科",
      "呼吸器内科",
      "循環器内科",
      "消化器内科",
      "外科",
      "脳神経外科",
      "肛門外科",
      "整形外科",
      "眼科",
      "耳鼻いんこう科",
      "皮膚科",
      "泌尿器科",
      "リウマチ科",
      "リハビリテーション科",
      "放射線科"
    ]
  },
  {
    "id": "2411240000860",
    "name": "北勢病院",
    "tel": "2411240000860",
    "url": "https://www.hokusei-hospital.jp",
    "address": "三重県いなべ市北勢町麻生田１５２５",
    "pref": "三重県",
    "city": "いなべ市北勢町麻生田",
    "kind": "hospital",
    "departments": [
      "内科",
      "精神科",
      "心療内科"
    ]
  },
  {
    "id": "2411240000060",
    "name": "伊賀市立上野総合市民病院",
    "tel": "2411240000060",
    "url": "http://www.cgh-iga.jp/",
    "address": "三重県伊賀市四十九町８３１",
    "pref": "三重県",
    "city": "伊賀市四十九町",
    "kind": "hospital",
    "departments": [
      "内科",
      "脳神経内科",
      "循環器内科",
      "消化器内科",
      "腫瘍内科",
      "外科",
      "脳神経外科",
      "整形外科",
      "小児科",
      "婦人科",
      "眼科",
      "耳鼻いんこう科",
      "皮膚科",
      "泌尿器科",
      "リハビリテーション科",
      "救急科"
    ]
  },
  {
    "id": "2411240001170",
    "name": "一般財団法人　信貴山病院　分院　上野病院",
    "tel": "2411240001170",
    "url": "http://www.heartland.or.jp/ueno/",
    "address": "三重県伊賀市四十九町２８８８",
    "pref": "三重県",
    "city": "伊賀市四十九町",
    "kind": "hospital",
    "departments": [
      "精神科",
      "神経科",
      "心療内科"
    ]
  },
  {
    "id": "2411249000014",
    "name": "社会医療法人　畿内会　岡波総合病院",
    "tel": "2411249000014",
    "url": "http://www.okanami.com/",
    "address": "三重県伊賀市上之庄２７１１番地１",
    "pref": "三重県",
    "city": "伊賀市上之庄",
    "kind": "hospital",
    "departments": [
      "内科",
      "呼吸器内科",
      "循環器内科",
      "消化器内科",
      "神経内科",
      "外科",
      "脳神経外科",
      "心臓血管外科",
      "整形外科",
      "小児科",
      "産婦人科",
      "眼科",
      "耳鼻いんこう科",
      "皮膚科",
      "泌尿器科",
      "歯科口腔外科",
      "放射線科",
      "麻酔科"
    ]
  },
  {
    "id": "2411240000580",
    "name": "医療法人　森川病院",
    "tel": "2411240000580",
    "url": "http://www.morikawa-wh.jp/",
    "address": "三重県伊賀市上野忍町２５１６－７",
    "pref": "三重県",
    "city": "伊賀市上野忍町",
    "kind": "hospital",
    "departments": [
      "内科",
      "整形外科",
      "小児科",
      "産科",
      "婦人科"
    ]
  },
  {
    "id": "2411249000016",
    "name": "医療法人全心会　伊勢ひかり病院",
    "tel": "2411249000016",
    "url": "https://ise-hikari.com",
    "address": "三重県伊勢市御薗町高向８１０番地１",
    "pref": "三重県",
    "city": "伊勢市御薗町高向",
    "kind": "hospital",
    "departments": [
      "内科",
      "神経内科",
      "外科",
      "脳神経外科",
      "整形外科",
      "形成外科",
      "小児科",
      "婦人科",
      "皮膚科",
      "泌尿器科",
      "リハビリテーション科"
    ]
  },
  {
    "id": "2411240001250",
    "name": "伊勢赤十字病院",
    "tel": "2411240001250",
    "url": "http://www.ise.jrc.or.jp",
    "address": "三重県伊勢市船江１丁目４７１番２",
    "pref": "三重県",
    "city": "伊勢市船江",
    "kind": "hospital",
    "departments": [
      "感染症内科",
      "血液内科",
      "糖尿病",
      "代謝内科",
      "脳神経内科",
      "呼吸器内科",
      "循環器内科",
      "消化器内科",
      "腎臓内科",
      "肝臓内科",
      "腫瘍内科",
      "緩和ケア内科",
      "外科",
      "脳神経外科",
      "呼吸器外科",
      "心臓血管外科",
      "乳腺外科",
      "整形外科",
      "形成外科",
      "小児科",
      "産婦人科",
      "眼科",
      "頭頸部",
      "耳鼻いんこう科",
      "皮膚科",
      "泌尿器科",
      "歯科口腔外科",
      "リハビリテーション科",
      "放射線診断科",
      "放射線治療科",
      "病理診断科",
      "麻酔科"
    ]
  },
  {
    "id": "2411249000004",
    "name": "伊勢田中病院",
    "tel": "2411249000004",
    "url": "https://www.isetanaka.jp/",
    "address": "三重県伊勢市大世古４丁目６番４７号",
    "pref": "三重県",
    "city": "伊勢市大世古",
    "kind": "hospital",
    "departments": [
      "内科",
      "呼吸器内科",
      "循環器内科",
      "腎臓内科",
      "外科",
      "消化器外科",
      "整形外科"
    ]
  },
  {
    "id": "2411240000020",
    "name": "市立伊勢総合病院",
    "tel": "2411240000020",
    "url": "https://hospital.city.ise.mie.jp/",
    "address": "三重県伊勢市楠部町３０３８",
    "pref": "三重県",
    "city": "伊勢市楠部町",
    "kind": "hospital",
    "departments": [
      "内科",
      "脳神経内科",
      "循環器内科",
      "緩和ケア内科",
      "外科",
      "脳神経外科",
      "消化器外科",
      "整形外科",
      "形成外科",
      "小児科",
      "婦人科",
      "眼科",
      "耳鼻いんこう科",
      "皮膚科",
      "泌尿器科",
      "精神科",
      "歯科口腔外科",
      "リハビリテーション科",
      "放射線科",
      "麻酔科"
    ]
  },
  {
    "id": "2411240000830",
    "name": "医療法人　大仲会　大仲さつき病院",
    "tel": "2411240000830",
    "url": "http://www.ohnaka-h.jp",
    "address": "三重県員弁郡東員町穴太２０００",
    "pref": "三重県",
    "city": "員弁郡東員町穴太",
    "kind": "hospital",
    "departments": [
      "精神科",
      "歯科"
    ]
  },
  {
    "id": "2411240000850",
    "name": "東員病院",
    "tel": "2411240000850",
    "url": "https://toin-hosp.jp",
    "address": "三重県員弁郡東員町穴太２４００",
    "pref": "三重県",
    "city": "員弁郡東員町穴太",
    "kind": "hospital",
    "departments": [
      "内科",
      "精神科",
      "神経科"
    ]
  },
  {
    "id": "2411240000150",
    "name": "亀山市立医療センター",
    "tel": "2411240000150",
    "url": "http://www.city.kameyama.mie.jp/iryo/",
    "address": "三重県亀山市亀田町４６６－１",
    "pref": "三重県",
    "city": "亀山市亀田町",
    "kind": "hospital",
    "departments": [
      "内科",
      "外科",
      "整形外科",
      "眼科"
    ]
  },
  {
    "id": "2411249000018",
    "name": "医療法人真正会　田中病院",
    "tel": "2411249000018",
    "url": "",
    "address": "三重県亀山市西丸町５３９",
    "pref": "三重県",
    "city": "亀山市西丸町",
    "kind": "hospital",
    "departments": [
      "内科",
      "皮膚科"
    ]
  },
  {
    "id": "2411240001210",
    "name": "亀山回生病院",
    "tel": "2411240001210",
    "url": "http://www.kaiseihp.com/1_kameyama/",
    "address": "三重県亀山市東御幸町２３２番地",
    "pref": "三重県",
    "city": "亀山市東御幸町",
    "kind": "hospital",
    "departments": [
      "内科",
      "整形外科"
    ]
  },
  {
    "id": "2411240001160",
    "name": "医療法人紀南会　熊野病院",
    "tel": "2411240001160",
    "url": "https://www.kumano-hp.jp/",
    "address": "三重県熊野市久生屋町８６８番地",
    "pref": "三重県",
    "city": "熊野市久生屋町",
    "kind": "hospital",
    "departments": [
      "内科",
      "精神科"
    ]
  },
  {
    "id": "2411249000012",
    "name": "ヨナハ丘の上病院",
    "tel": "2411249000012",
    "url": "https://yonaha.or.jp",
    "address": "三重県桑名市さくらの丘１番地",
    "pref": "三重県",
    "city": "桑名市さくらの丘",
    "kind": "hospital",
    "departments": [
      "内科",
      "呼吸器内科",
      "循環器内科",
      "消化器内科",
      "胃腸内科",
      "外科",
      "脳神経外科",
      "肛門外科",
      "整形外科",
      "小児科",
      "産婦人科",
      "眼科",
      "泌尿器科",
      "リウマチ科",
      "リハビリテーション科",
      "麻酔科"
    ]
  },
  {
    "id": "2411240000230",
    "name": "医療法人　桑名病院",
    "tel": "2411240000230",
    "url": "http://kuwana-hosp.jp/",
    "address": "三重県桑名市京橋町３０",
    "pref": "三重県",
    "city": "桑名市京橋町",
    "kind": "hospital",
    "departments": [
      "内科",
      "呼吸器内科",
      "循環器内科",
      "消化器内科",
      "胃腸内科",
      "外科",
      "整形外科",
      "小児科",
      "耳鼻いんこう科",
      "リハビリテーション科"
    ]
  },
  {
    "id": "2411240000590",
    "name": "医療法人　誠会　山崎病院",
    "tel": "2411240000590",
    "url": "",
    "address": "三重県桑名市江場１３６５",
    "pref": "三重県",
    "city": "桑名市江場",
    "kind": "hospital",
    "departments": [
      "内科",
      "消化器内科",
      "外科",
      "整形外科",
      "泌尿器科",
      "リハビリテーション科"
    ]
  },
  {
    "id": "2411240000620",
    "name": "桑名市総合医療センター",
    "tel": "2411240000620",
    "url": "https://www.kuwanacmc.or.jp",
    "address": "三重県桑名市寿町３－１１",
    "pref": "三重県",
    "city": "桑名市寿町",
    "kind": "hospital",
    "departments": [
      "内科",
      "血液内科",
      "糖尿病",
      "内分泌内科",
      "脳神経内科",
      "呼吸器内科",
      "循環器内科",
      "消化器内科",
      "腎臓内科",
      "肝臓内科",
      "膠原病リウマチ内科",
      "外科",
      "脳神経外科",
      "呼吸器外科",
      "心臓血管外科",
      "消化器外科",
      "乳腺外科",
      "整形外科",
      "形成外科",
      "小児科",
      "産婦人科",
      "眼科",
      "耳鼻いんこう科",
      "皮膚科",
      "泌尿器科",
      "精神科",
      "歯科口腔外科",
      "リウマチ科",
      "リハビリテーション科",
      "放射線科",
      "病理診断科",
      "救急科",
      "麻酔科",
      "総合診療科"
    ]
  },
  {
    "id": "2411249000010",
    "name": "医療法人社団　橘会　多度あやめ病院",
    "tel": "2411249000010",
    "url": "http://www.tadoayame.or.jp/index.htm",
    "address": "三重県桑名市多度町柚井１７０２",
    "pref": "三重県",
    "city": "桑名市多度町柚井",
    "kind": "hospital",
    "departments": [
      "内科",
      "児童精神科",
      "精神科"
    ]
  },
  {
    "id": "2411240000010",
    "name": "青木記念病院",
    "tel": "2411240000010",
    "url": "http://www.aoki-hp.com/",
    "address": "三重県桑名市中央町５－７",
    "pref": "三重県",
    "city": "桑名市中央町",
    "kind": "hospital",
    "departments": [
      "内科",
      "内分泌内科",
      "脳神経内科",
      "呼吸器内科",
      "循環器内科",
      "消化器内科",
      "外科",
      "脳神経外科",
      "心臓血管外科",
      "消化器外科",
      "乳腺",
      "内分泌外科",
      "整形外科",
      "形成外科",
      "小児科",
      "皮膚科",
      "泌尿器科",
      "リウマチ科",
      "リハビリテーション科",
      "麻酔科"
    ]
  },
  {
    "id": "2411240000820",
    "name": "医療法人（社団）　佐藤病院　長島中央病院",
    "tel": "2411240000820",
    "url": "https://www.sato-group.jp/cyuo/",
    "address": "三重県桑名市長島町福吉２７１",
    "pref": "三重県",
    "city": "桑名市長島町福吉",
    "kind": "hospital",
    "departments": [
      "内科",
      "外科",
      "歯科",
      "リハビリテーション科"
    ]
  },
  {
    "id": "2411240000570",
    "name": "医療法人　普照会　もりえい病院",
    "tel": "2411240000570",
    "url": "http://www.moriei.jp",
    "address": "三重県桑名市内堀２８－１",
    "pref": "三重県",
    "city": "桑名市内堀",
    "kind": "hospital",
    "departments": [
      "内科",
      "循環器内科",
      "消化器内科",
      "外科",
      "気管食道外科",
      "血管外科",
      "消化器外科",
      "肛門外科",
      "整形外科",
      "緩和ケア外科",
      "小児科",
      "婦人科",
      "皮膚科",
      "心療内科",
      "歯科",
      "矯正歯科",
      "歯科口腔外科",
      "小児歯科",
      "アレルギー科",
      "リハビリテーション科",
      "放射線科",
      "麻酔科"
    ]
  },
  {
    "id": "2411240000260",
    "name": "三重県厚生農業協同組合連合会三重北医療センター　菰野厚生病院",
    "tel": "2411240000260",
    "url": "http://www.miekosei.or.jp/3_kkh/",
    "address": "三重県三重郡菰野町福村７５",
    "pref": "三重県",
    "city": "三重郡菰野町福村",
    "kind": "hospital",
    "departments": [
      "内科",
      "脳神経内科",
      "呼吸器内科",
      "循環器内科",
      "消化器内科",
      "外科",
      "脳神経外科",
      "血管外科",
      "肛門外科",
      "整形外科",
      "婦人科",
      "眼科",
      "耳鼻いんこう科",
      "皮膚科",
      "泌尿器科",
      "リハビリテーション科",
      "放射線科"
    ]
  },
  {
    "id": "2411240000640",
    "name": "独立行政法人　地域医療機能推進機構　四日市羽津医療センター",
    "tel": "2411240000640",
    "url": "http://yokkaichi.jcho.go.jp/",
    "address": "三重県四日市市羽津山町１０－８",
    "pref": "三重県",
    "city": "四日市市羽津山町",
    "kind": "hospital",
    "departments": [
      "内科",
      "糖尿病",
      "内分泌内科",
      "脳神経内科",
      "呼吸器内科",
      "循環器内科",
      "消化器内科",
      "腎臓内科",
      "外科",
      "乳腺外科",
      "整形外科",
      "小児科",
      "婦人科",
      "眼科",
      "耳鼻いんこう科",
      "皮膚科",
      "泌尿器科",
      "精神科",
      "リウマチ科",
      "放射線科",
      "病理診断科",
      "麻酔科",
      "緩和ケア科"
    ]
  },
  {
    "id": "2411240001300",
    "name": "医療法人社団プログレス四日市消化器病センター",
    "tel": "2411240001300",
    "url": "http://www.yokkaichi-shoukaki.com/news/745/",
    "address": "三重県四日市市下海老町字高松１８５－３",
    "pref": "三重県",
    "city": "四日市市下海老町字高松",
    "kind": "hospital",
    "departments": [
      "糖尿病内科",
      "胃腸内科",
      "腎臓内科",
      "人工透析内科",
      "肝臓内科",
      "内視鏡内科",
      "整形外科",
      "眼科",
      "泌尿器科",
      "リハビリテーション科"
    ]
  },
  {
    "id": "2411240001280",
    "name": "医療法人　徳新会　四日市徳新会病院",
    "tel": "2411240001280",
    "url": "http://yok-toku.jp",
    "address": "三重県四日市市久保田二丁目１番２号",
    "pref": "三重県",
    "city": "四日市市久保田二",
    "kind": "hospital",
    "departments": [
      "内科",
      "呼吸器内科",
      "神経内科",
      "精神科",
      "リハビリテーション科"
    ]
  },
  {
    "id": "2411240000110",
    "name": "医療法人社団主体会　小山田記念温泉病院",
    "tel": "2411240000110",
    "url": "http://www.syutaikai.jp",
    "address": "三重県四日市市山田町５５３８－１",
    "pref": "三重県",
    "city": "四日市市山田町",
    "kind": "hospital",
    "departments": [
      "内科",
      "脳神経内科",
      "循環器内科",
      "整形外科",
      "眼科",
      "耳鼻いんこう科",
      "皮膚科",
      "泌尿器科",
      "歯科"
    ]
  },
  {
    "id": "2411240000320",
    "name": "市立四日市病院",
    "tel": "2411240000320",
    "url": "http://www.city.yokkaichi.mie.jp/hospital/",
    "address": "三重県四日市市芝田２－２－３７",
    "pref": "三重県",
    "city": "四日市市芝田",
    "kind": "hospital",
    "departments": [
      "内科",
      "血液内科",
      "糖尿病",
      "内分泌内科",
      "脳神経内科",
      "呼吸器内科",
      "循環器内科",
      "消化器内科",
      "腎臓内科",
      "外科",
      "脳神経外科",
      "呼吸器外科",
      "心臓血管外科",
      "消化器外科",
      "乳腺外科",
      "整形外科",
      "形成外科",
      "小児科",
      "産婦人科",
      "眼科",
      "耳鼻いんこう科",
      "皮膚科",
      "泌尿器科",
      "精神科",
      "歯科口腔外科",
      "リハビリテーション科",
      "放射線科",
      "病理診断科",
      "麻酔科"
    ]
  },
  {
    "id": "2411240000610",
    "name": "医療法人社団　山中胃腸科病院",
    "tel": "2411240000610",
    "url": "http://www.yamanaka-hsp.or.jp/index.php",
    "address": "三重県四日市市小古曽３－５－３３",
    "pref": "三重県",
    "city": "四日市市小古曽",
    "kind": "hospital",
    "departments": [
      "内科",
      "循環器内科",
      "消化器内科",
      "漢方内科",
      "外科",
      "消化器外科",
      "整形外科",
      "眼科",
      "泌尿器科",
      "リハビリテーション科",
      "放射線科",
      "臨床検査科"
    ]
  },
  {
    "id": "2411240000180",
    "name": "医療法人社団主体会　主体会病院",
    "tel": "2411240000180",
    "url": "http://www.syutaikai.jp",
    "address": "三重県四日市市城北町８－１",
    "pref": "三重県",
    "city": "四日市市城北町",
    "kind": "hospital",
    "departments": [
      "内科",
      "脳神経内科",
      "呼吸器内科",
      "循環器内科",
      "消化器内科",
      "腎臓内科",
      "人工透析内科",
      "外科",
      "脳神経外科",
      "整形外科",
      "皮膚科",
      "リハビリテーション科",
      "放射線科"
    ]
  },
  {
    "id": "2411240000890",
    "name": "医療法人安仁会　水沢病院",
    "tel": "2411240000890",
    "url": "http://suizawahp.com/",
    "address": "三重県四日市市水沢町６３８－３",
    "pref": "三重県",
    "city": "四日市市水沢町",
    "kind": "hospital",
    "departments": [
      "内科",
      "循環器内科",
      "精神科",
      "神経科"
    ]
  },
  {
    "id": "2411240000790",
    "name": "医療法人　尚豊会　みたき総合病院",
    "tel": "2411240000790",
    "url": "https://mitaki.or.jp/",
    "address": "三重県四日市市生桑町菰池４５８－１",
    "pref": "三重県",
    "city": "四日市市生桑町菰池",
    "kind": "hospital",
    "departments": [
      "内科",
      "糖尿病内科",
      "循環器内科",
      "消化器内科",
      "腎臓内科",
      "神経内科",
      "緩和ケア内科",
      "外科",
      "脳神経外科",
      "血管外科",
      "乳腺外科",
      "整形外科",
      "小児科",
      "産婦人科",
      "眼科",
      "耳鼻いんこう科",
      "泌尿器科",
      "歯科口腔外科",
      "小児歯科",
      "アレルギー科",
      "リウマチ科",
      "リハビリテーション科",
      "麻酔科"
    ]
  },
  {
    "id": "2411240000540",
    "name": "三重県立総合医療センター",
    "tel": "2411240000540",
    "url": "https://www.mie-gmc.jp/",
    "address": "三重県四日市市大字日永５４５０－１３２",
    "pref": "三重県",
    "city": "四日市市大字日永",
    "kind": "hospital",
    "departments": [
      "内科",
      "感染症内科",
      "血液内科",
      "脳神経内科",
      "呼吸器内科",
      "循環器内科",
      "消化器内科",
      "腎臓内科",
      "疼痛緩和内科",
      "外科",
      "脳神経外科",
      "脳外科",
      "呼吸器外科",
      "心臓血管外科",
      "消化器外科",
      "乳腺外科",
      "整形外科",
      "形成外科",
      "小児科",
      "小児外科",
      "産婦人科",
      "眼科",
      "耳鼻いんこう科",
      "皮膚科",
      "泌尿器科",
      "精神科",
      "放射線診断科",
      "放射線治療科",
      "病理診断科",
      "救急科",
      "麻酔科"
    ]
  },
  {
    "id": "2411240000670",
    "name": "医療法人　石田会　石田胃腸科病院",
    "tel": "2411240000670",
    "url": "http://www.myclinic.ne.jp/ishida_i/",
    "address": "三重県四日市市朝日町１－１５",
    "pref": "三重県",
    "city": "四日市市朝日町",
    "kind": "hospital",
    "departments": [
      "内科",
      "消化器内科",
      "胃腸内科",
      "外科",
      "肛門外科"
    ]
  },
  {
    "id": "2411240000900",
    "name": "社会医療法人　居仁会　総合心療センターひなが",
    "tel": "2411240000900",
    "url": "https://hinaga.or.jp",
    "address": "三重県四日市市日永５０３９番地",
    "pref": "三重県",
    "city": "四日市市日永",
    "kind": "hospital",
    "departments": [
      "内科",
      "児童精神科",
      "美容皮膚科",
      "精神科",
      "心療内科",
      "歯科"
    ]
  },
  {
    "id": "2411240000410",
    "name": "医療法人　富田浜病院",
    "tel": "2411240000410",
    "url": "http://www.tomidahama.jp",
    "address": "三重県四日市市富田浜町２６－１４",
    "pref": "三重県",
    "city": "四日市市富田浜町",
    "kind": "hospital",
    "departments": [
      "内科",
      "脳神経内科",
      "外科",
      "脳神経外科",
      "整形外科",
      "リハビリテーション科"
    ]
  },
  {
    "id": "2411240000530",
    "name": "三重県立志摩病院",
    "tel": "2411240000530",
    "url": "http://kenritsushima.jadecom.or.jp/",
    "address": "三重県志摩市阿児町鵜方１２５７",
    "pref": "三重県",
    "city": "志摩市阿児町鵜方",
    "kind": "hospital",
    "departments": [
      "内科",
      "脳神経内科",
      "循環器内科",
      "漢方内科",
      "緩和ケア内科",
      "外科",
      "脳神経外科",
      "整形外科",
      "形成外科",
      "小児科",
      "産婦人科",
      "眼科",
      "耳鼻いんこう科",
      "皮膚科",
      "泌尿器科",
      "精神科",
      "放射線科"
    ]
  },
  {
    "id": "2411240001150",
    "name": "医療法人　豊和会　豊和病院",
    "tel": "2411240001150",
    "url": "https://houwakai.or.jp/",
    "address": "三重県志摩市阿児町鵜方２５５５－９",
    "pref": "三重県",
    "city": "志摩市阿児町鵜方",
    "kind": "hospital",
    "departments": [
      "内科",
      "消化器内科",
      "婦人科",
      "泌尿器科"
    ]
  },
  {
    "id": "2411240000340",
    "name": "国民健康保険志摩市民病院",
    "tel": "2411240000340",
    "url": "https://shimacityhospital.jp",
    "address": "三重県志摩市大王町波切１９４１－１",
    "pref": "三重県",
    "city": "志摩市大王町波切",
    "kind": "hospital",
    "departments": [
      "内科",
      "循環器内科",
      "消化器内科",
      "外科",
      "整形外科",
      "皮膚科",
      "リハビリテーション科"
    ]
  },
  {
    "id": "2411240000780",
    "name": "松阪厚生病院",
    "tel": "2411240000780",
    "url": "http://www.matsusaka-kousei.com",
    "address": "三重県松阪市久保町１９２７－２",
    "pref": "三重県",
    "city": "松阪市久保町",
    "kind": "hospital",
    "departments": [
      "内科",
      "循環器内科",
      "消化器内科",
      "腎臓内科",
      "人工透析内科",
      "ペインクリニック内科",
      "外科",
      "整形外科",
      "眼科",
      "皮膚科",
      "精神科",
      "心療内科",
      "歯科",
      "リハビリテーション科"
    ]
  },
  {
    "id": "2411240001080",
    "name": "南勢病院",
    "tel": "2411240001080",
    "url": "https://www.nansei-hospital.jp",
    "address": "三重県松阪市山室町２２７５",
    "pref": "三重県",
    "city": "松阪市山室町",
    "kind": "hospital",
    "departments": [
      "内科",
      "脳神経内科",
      "児童精神科",
      "皮膚科",
      "泌尿器科",
      "精神科",
      "心療内科",
      "老年精神科",
      "歯科",
      "リハビリテーション科"
    ]
  },
  {
    "id": "2411240001100",
    "name": "花の丘病院",
    "tel": "2411240001100",
    "url": "http://www.shoutoku.or.jp",
    "address": "三重県松阪市山室町７０７－３",
    "pref": "三重県",
    "city": "松阪市山室町",
    "kind": "hospital",
    "departments": [
      "内科",
      "人工透析内科",
      "整形外科",
      "婦人科",
      "リハビリテーション科"
    ]
  },
  {
    "id": "2411240000510",
    "name": "三重県厚生農業協同組合連合会　松阪中央総合病院",
    "tel": "2411240000510",
    "url": "http://www.miekosei.or.jp/1_mch/index.html",
    "address": "三重県松阪市川井町字小望１０２",
    "pref": "三重県",
    "city": "松阪市川井町字小望",
    "kind": "hospital",
    "departments": [
      "内科",
      "血液内科",
      "脳神経内科",
      "呼吸器内科",
      "循環器内科",
      "消化器内科",
      "外科",
      "脳神経外科",
      "心臓血管外科",
      "胸部外科",
      "整形外科",
      "小児科",
      "産婦人科",
      "眼科",
      "耳鼻いんこう科",
      "皮膚科",
      "泌尿器科",
      "精神科",
      "リハビリテーション科",
      "放射線治療科",
      "病理診断科",
      "麻酔科"
    ]
  },
  {
    "id": "2411240000130",
    "name": "社会福祉法人　恩賜財団　済生会松阪総合病院",
    "tel": "2411240000130",
    "url": "http://www.matsusaka.saiseikai.or.jp",
    "address": "三重県松阪市朝日町一区１５－６",
    "pref": "三重県",
    "city": "松阪市朝日町一区",
    "kind": "hospital",
    "departments": [
      "内科",
      "脳神経内科",
      "呼吸器内科",
      "循環器内科",
      "消化器内科",
      "腎臓内科",
      "外科",
      "脳神経外科",
      "消化器外科",
      "乳腺外科",
      "整形外科",
      "形成外科",
      "小児科",
      "産婦人科",
      "眼科",
      "耳鼻いんこう科",
      "皮膚科",
      "泌尿器科",
      "精神科",
      "歯科",
      "歯科口腔外科",
      "リウマチ科",
      "リハビリテーション科",
      "放射線科",
      "病理診断科",
      "臨床検査科",
      "救急科",
      "麻酔科"
    ]
  },
  {
    "id": "2411240000500",
    "name": "松阪市民病院",
    "tel": "2411240000500",
    "url": "http://www.city.matsusaka.mie.jp/site/hosannai/",
    "address": "三重県松阪市殿町１５５０",
    "pref": "三重県",
    "city": "松阪市殿町",
    "kind": "hospital",
    "departments": [
      "内科",
      "呼吸器内科",
      "循環器内科",
      "消化器内科",
      "神経内科",
      "外科",
      "脳神経外科",
      "呼吸器外科",
      "消化器外科",
      "整形外科",
      "形成外科",
      "小児科",
      "産婦人科",
      "眼科",
      "耳鼻いんこう科",
      "皮膚科",
      "泌尿器科",
      "精神科",
      "歯科口腔外科",
      "リウマチ科",
      "リハビリテーション科",
      "放射線科",
      "病理診断科",
      "救急科",
      "麻酔科"
    ]
  },
  {
    "id": "2411240000720",
    "name": "医療法人　桜木記念病院",
    "tel": "2411240000720",
    "url": "http://www.sakuragi-hp.com/",
    "address": "三重県松阪市南町４４３－４",
    "pref": "三重県",
    "city": "松阪市南町",
    "kind": "hospital",
    "departments": [
      "内科",
      "呼吸器内科",
      "循環器内科",
      "胃腸内科",
      "小児科",
      "皮膚科",
      "リハビリテーション科"
    ]
  },
  {
    "id": "2411240000080",
    "name": "三重県厚生農業協同組合連合会　大台厚生病院",
    "tel": "2411240000080",
    "url": "http://www.miekosei.or.jp/5_okh/",
    "address": "三重県多気郡大台町上三瀬６６３－２",
    "pref": "三重県",
    "city": "多気郡大台町上三瀬",
    "kind": "hospital",
    "departments": [
      "内科",
      "循環器内科",
      "胃腸内科",
      "脳神経外科",
      "整形外科",
      "形成外科",
      "眼科",
      "耳鼻いんこう科",
      "皮膚科",
      "泌尿器科"
    ]
  },
  {
    "id": "2411240001060",
    "name": "社会福祉法人　恩賜財団　済生会　明和病院",
    "tel": "2411240001060",
    "url": "http://www.meiwa-saiseikai.jp",
    "address": "三重県多気郡明和町上野４３５",
    "pref": "三重県",
    "city": "多気郡明和町上野",
    "kind": "hospital",
    "departments": [
      "内科",
      "脳神経内科",
      "呼吸器内科",
      "外科",
      "脳神経外科",
      "消化器外科",
      "整形外科",
      "小児科",
      "眼科",
      "泌尿器科",
      "リハビリテーション科"
    ]
  },
  {
    "id": "2411240001180",
    "name": "三重ハートセンター",
    "tel": "2411240001180",
    "url": "http://www.mie-heartcenter.com",
    "address": "三重県多気郡明和町大淀２２２７－１",
    "pref": "三重県",
    "city": "多気郡明和町大淀",
    "kind": "hospital",
    "departments": [
      "内科",
      "循環器内科",
      "心臓血管外科",
      "放射線科",
      "麻酔科"
    ]
  },
  {
    "id": "2411249000013",
    "name": "武内病院",
    "tel": "2411249000013",
    "url": "https://takeuchi-hosp.jp",
    "address": "三重県津市一色町２１５－１",
    "pref": "三重県",
    "city": "津市一色町",
    "kind": "hospital",
    "departments": [
      "内科",
      "血液内科",
      "循環器内科",
      "消化器内科",
      "腎臓内科",
      "神経内科",
      "外科",
      "整形外科",
      "泌尿器科",
      "リハビリテーション科",
      "放射線科"
    ]
  },
  {
    "id": "2411240000050",
    "name": "医療法人　思源会　岩崎病院",
    "tel": "2411240000050",
    "url": "http://www.iwasaki-hosp.or.jp",
    "address": "三重県津市一身田町３３３",
    "pref": "三重県",
    "city": "津市一身田町",
    "kind": "hospital",
    "departments": [
      "内科",
      "呼吸器内科",
      "循環器内科",
      "消化器内科",
      "神経内科",
      "外科",
      "脳神経外科",
      "整形外科",
      "皮膚科",
      "リハビリテーション科"
    ]
  },
  {
    "id": "2411249000005",
    "name": "倉本内科病院",
    "tel": "2411249000005",
    "url": "http://www.kuramotohospital.net/",
    "address": "三重県津市下弁財町津興３０４０",
    "pref": "三重県",
    "city": "津市下弁財町津興",
    "kind": "hospital",
    "departments": [
      "内科",
      "呼吸器内科",
      "循環器内科",
      "消化器内科"
    ]
  },
  {
    "id": "2411240001000",
    "name": "医療法人　井上内科病院",
    "tel": "2411240001000",
    "url": "http://www.inoue-med.com",
    "address": "三重県津市久居井戸山町７５９",
    "pref": "三重県",
    "city": "津市久居井戸山町",
    "kind": "hospital",
    "departments": [
      "内科",
      "呼吸器内科",
      "精神科",
      "心療内科"
    ]
  },
  {
    "id": "2411240000240",
    "name": "独立行政法人国立病院機構　三重中央医療センター",
    "tel": "2411240000240",
    "url": "https://miechuo.hosp.go.jp",
    "address": "三重県津市久居明神町２１５８－５",
    "pref": "三重県",
    "city": "津市久居明神町",
    "kind": "hospital",
    "departments": [
      "糖尿病内科",
      "呼吸器内科",
      "循環器内科",
      "消化器内科",
      "腎臓内科",
      "肝臓内科",
      "神経内科",
      "外科",
      "脳神経外科",
      "呼吸器外科",
      "心臓血管外科",
      "消化器外科",
      "乳腺外科",
      "整形外科",
      "形成外科",
      "小児科",
      "産科",
      "婦人科",
      "眼科",
      "耳鼻いんこう科",
      "皮膚科",
      "泌尿器科",
      "精神科",
      "歯科",
      "歯科口腔外科",
      "リウマチ科",
      "リハビリテーション科",
      "放射線科",
      "麻酔科"
    ]
  },
  {
    "id": "2411240000630",
    "name": "医療法人　吉田クリニック",
    "tel": "2411240000630",
    "url": "https://yoshida-clinic.or.jp",
    "address": "三重県津市栗真中山町下沢７９－５",
    "pref": "三重県",
    "city": "津市栗真中山町下沢",
    "kind": "hospital",
    "departments": [
      "内科",
      "呼吸器内科",
      "循環器内科",
      "胃腸内科",
      "神経内科",
      "外科",
      "肛門外科",
      "整形外科",
      "小児科",
      "リハビリテーション科"
    ]
  },
  {
    "id": "2411240001030",
    "name": "医療法人　久居病院",
    "tel": "2411240001030",
    "url": "https://hisai-hospital.or.jp",
    "address": "三重県津市戸木町５０４３",
    "pref": "三重県",
    "city": "津市戸木町",
    "kind": "hospital",
    "departments": [
      "精神科",
      "心療内科"
    ]
  },
  {
    "id": "2411240000550",
    "name": "国立大学法人　三重大学医学部附属病院",
    "tel": "2411240000550",
    "url": "https://www.hosp.mie-u.ac.jp",
    "address": "三重県津市江戸橋２－１７４",
    "pref": "三重県",
    "city": "津市江戸橋",
    "kind": "hospital",
    "departments": [
      "内科",
      "感染症内科",
      "血液内科",
      "糖尿病",
      "内分泌内科",
      "脳神経内科",
      "呼吸器内科",
      "循環器内科",
      "消化器内科",
      "腎臓内科",
      "腫瘍内科",
      "漢方内科",
      "緩和ケア内科",
      "外科",
      "脳神経外科",
      "呼吸器外科",
      "心臓血管外科",
      "消化器外科",
      "乳腺外科",
      "移植外科",
      "整形外科",
      "形成外科",
      "小児科",
      "小児外科",
      "産婦人科",
      "眼科",
      "頭頸部",
      "耳鼻いんこう科",
      "皮膚科",
      "腎臓",
      "泌尿器科",
      "精神科",
      "歯科口腔外科",
      "リウマチ科",
      "リハビリテーション科",
      "放射線科",
      "病理診断科",
      "救急科",
      "麻酔科"
    ]
  },
  {
    "id": "2411240000270",
    "name": "榊原温泉病院",
    "tel": "2411240000270",
    "url": "http://www.sakaki-hosp.jp/",
    "address": "三重県津市榊原町１０３３－４",
    "pref": "三重県",
    "city": "津市榊原町",
    "kind": "hospital",
    "departments": [
      "内科",
      "脳神経内科",
      "泌尿器科"
    ]
  },
  {
    "id": "2411240000690",
    "name": "医療法人　凰林会　榊原白鳳病院",
    "tel": "2411240000690",
    "url": "http://www.ohrin-mc.jp/hakuho",
    "address": "三重県津市榊原町５６３０",
    "pref": "三重県",
    "city": "津市榊原町",
    "kind": "hospital",
    "departments": [
      "内科",
      "脳神経内科",
      "循環器内科",
      "外科",
      "整形外科",
      "歯科",
      "リウマチ科"
    ]
  },
  {
    "id": "2411240001020",
    "name": "独立行政法人　国立病院機構　榊原病院",
    "tel": "2411240001020",
    "url": "https://sakakibara.hosp.go.jp/",
    "address": "三重県津市榊原町７７７",
    "pref": "三重県",
    "city": "津市榊原町",
    "kind": "hospital",
    "departments": [
      "精神科"
    ]
  },
  {
    "id": "2411249000017",
    "name": "みえ医療福祉生活協同組合　津生協病院",
    "tel": "2411249000017",
    "url": "http://www.tsucoop.jp",
    "address": "三重県津市寿町１６－２４",
    "pref": "三重県",
    "city": "津市寿町",
    "kind": "hospital",
    "departments": [
      "内科",
      "糖尿病内科",
      "循環器内科",
      "消化器内科",
      "神経内科",
      "外科",
      "乳腺外科",
      "肛門外科",
      "小児科",
      "リウマチ科"
    ]
  },
  {
    "id": "2411240000980",
    "name": "三重県立こころの医療センター",
    "tel": "2411240000980",
    "url": "http://www.pref.mie.lg.jp/KOKOROHP/HP/index.htm",
    "address": "三重県津市城山１－１２－１",
    "pref": "三重県",
    "city": "津市城山",
    "kind": "hospital",
    "departments": [
      "内科",
      "脳神経内科",
      "精神科",
      "歯科"
    ]
  },
  {
    "id": "2411240000420",
    "name": "医療法人　永井病院",
    "tel": "2411240000420",
    "url": "http://www.nagai-hp.or.jp/",
    "address": "三重県津市西丸之内２９－２９",
    "pref": "三重県",
    "city": "津市西丸之内",
    "kind": "hospital",
    "departments": [
      "内科",
      "循環器内科",
      "消化器内科",
      "腎臓内科",
      "神経内科",
      "外科",
      "心臓血管外科",
      "消化器外科",
      "乳腺外科",
      "整形外科",
      "形成外科",
      "婦人科",
      "泌尿器科",
      "リハビリテーション科",
      "放射線科",
      "救急科",
      "麻酔科"
    ]
  },
  {
    "id": "2411240000770",
    "name": "藤田医科大学七栗記念病院",
    "tel": "2411240000770",
    "url": "https://nanakuri.fujita-hu.ac.jp",
    "address": "三重県津市大鳥町４２４番地の－１",
    "pref": "三重県",
    "city": "津市大鳥町",
    "kind": "hospital",
    "departments": [
      "内科",
      "緩和ケア外科",
      "歯科",
      "リハビリテーション科"
    ]
  },
  {
    "id": "2411240000360",
    "name": "医療法人社団　雄飛会　大門病院",
    "tel": "2411240000360",
    "url": "http://daimon-hp.sakura.ne.jp/",
    "address": "三重県津市大門１－３",
    "pref": "三重県",
    "city": "津市大門",
    "kind": "hospital",
    "departments": [
      "内科",
      "外科",
      "脳神経外科",
      "整形外科",
      "リハビリテーション科",
      "麻酔科"
    ]
  },
  {
    "id": "2411240000250",
    "name": "独立行政法人　国立病院機構　三重病院",
    "tel": "2411240000250",
    "url": "https://mie.hosp.go.jp/",
    "address": "三重県津市大里窪田町３５７番地",
    "pref": "三重県",
    "city": "津市大里窪田町",
    "kind": "hospital",
    "departments": [
      "内科",
      "脳神経内科",
      "呼吸器内科",
      "整形外科",
      "小児科",
      "小児外科",
      "眼科",
      "耳鼻いんこう科",
      "心療内科",
      "歯科口腔外科",
      "アレルギー科",
      "リハビリテーション科"
    ]
  },
  {
    "id": "2411240001310",
    "name": "三重県立子ども心身発達医療センター",
    "tel": "2411240001310",
    "url": "http://www.pref.mie.lg.jp/CHILDC/",
    "address": "三重県津市大里窪田町３４０番５",
    "pref": "三重県",
    "city": "津市大里窪田町",
    "kind": "hospital",
    "departments": [
      "整形外科",
      "児童精神科",
      "リハビリテーション科"
    ]
  },
  {
    "id": "2411240000400",
    "name": "医療法人　同心会　遠山病院",
    "tel": "2411240000400",
    "url": "http://www.toyama-hp.jp/",
    "address": "三重県津市南新町１７－２２",
    "pref": "三重県",
    "city": "津市南新町",
    "kind": "hospital",
    "departments": [
      "内科",
      "呼吸器内科",
      "循環器内科",
      "消化器内科",
      "外科",
      "肛門外科"
    ]
  },
  {
    "id": "2411240001190",
    "name": "若葉病院",
    "tel": "2411240001190",
    "url": "http://www.wakabahsp.jp/",
    "address": "三重県津市南中央２８－１３",
    "pref": "三重県",
    "city": "津市南中央",
    "kind": "hospital",
    "departments": [
      "内科",
      "外科",
      "脳神経外科",
      "整形外科",
      "形成外科",
      "リハビリテーション科"
    ]
  },
  {
    "id": "2411240000030",
    "name": "三重県立一志病院",
    "tel": "2411240000030",
    "url": "http://www.pref.mie.lg.jp/IHOS/HP/",
    "address": "三重県津市白山町南家城６１６",
    "pref": "三重県",
    "city": "津市白山町南家城",
    "kind": "hospital",
    "departments": [
      "内科",
      "外科",
      "整形外科",
      "眼科"
    ]
  },
  {
    "id": "2411240000750",
    "name": "玉城町国民健康保険　玉城病院",
    "tel": "2411240000750",
    "url": "http://www.amigo2.ne.jp/~tamakihp/index.htm",
    "address": "三重県度会郡玉城町佐田８８１",
    "pref": "三重県",
    "city": "度会郡玉城町佐田",
    "kind": "hospital",
    "departments": [
      "内科",
      "外科",
      "整形外科",
      "眼科",
      "皮膚科",
      "リハビリテーション科",
      "麻酔科"
    ]
  },
  {
    "id": "2411249000007",
    "name": "町立南伊勢病院",
    "tel": "2411249000007",
    "url": "https://minamiise-hospital.com/",
    "address": "三重県度会郡南伊勢町船越２５４５",
    "pref": "三重県",
    "city": "度会郡南伊勢町船越",
    "kind": "hospital",
    "departments": [
      "内科",
      "脳神経内科",
      "外科",
      "整形外科",
      "小児科",
      "眼科",
      "皮膚科"
    ]
  },
  {
    "id": "2411240000190",
    "name": "紀南病院",
    "tel": "2411240000190",
    "url": "http://www.kinan-hp-mie.jp/",
    "address": "三重県南牟婁郡御浜町阿田和４７５０",
    "pref": "三重県",
    "city": "南牟婁郡御浜町阿田和",
    "kind": "hospital",
    "departments": [
      "内科",
      "脳神経内科",
      "外科",
      "脳神経外科",
      "整形外科",
      "小児科",
      "産婦人科",
      "眼科",
      "耳鼻いんこう科",
      "皮膚科",
      "泌尿器科",
      "歯科口腔外科",
      "リハビリテーション科",
      "放射線科"
    ]
  },
  {
    "id": "2411240000120",
    "name": "尾鷲総合病院",
    "tel": "2411240000120",
    "url": "http://owasehp.jp/",
    "address": "三重県尾鷲市上野町５－２５",
    "pref": "三重県",
    "city": "尾鷲市上野町",
    "kind": "hospital",
    "departments": [
      "内科",
      "脳神経内科",
      "循環器内科",
      "外科",
      "脳神経外科",
      "整形外科",
      "小児科",
      "産婦人科",
      "眼科",
      "耳鼻いんこう科",
      "皮膚科",
      "泌尿器科",
      "精神科",
      "放射線科"
    ]
  },
  {
    "id": "2411240000740",
    "name": "第一病院",
    "tel": "2411240000740",
    "url": "",
    "address": "三重県北牟婁郡紀北町上里２２５－８",
    "pref": "三重県",
    "city": "北牟婁郡紀北町上里",
    "kind": "hospital",
    "departments": [
      "内科",
      "外科",
      "整形外科",
      "リハビリテーション科"
    ]
  },
  {
    "id": "2411240000430",
    "name": "社会医療法人峰和会　長島回生病院",
    "tel": "2411240000430",
    "url": "http://www.kaiseihp.com/1_nagashima/",
    "address": "三重県北牟婁郡紀北町東長島２",
    "pref": "三重県",
    "city": "北牟婁郡紀北町東長島",
    "kind": "hospital",
    "departments": [
      "内科"
    ]
  },
  {
    "id": "2411240000680",
    "name": "医療法人（社団）　寺田病院",
    "tel": "2411240000680",
    "url": "http://www.terada-hp.or.jp",
    "address": "三重県名張市夏見３２６０番地１",
    "pref": "三重県",
    "city": "名張市夏見",
    "kind": "hospital",
    "departments": [
      "内科",
      "循環器内科",
      "消化器内科",
      "外科",
      "脳神経外科",
      "脳外科",
      "消化器外科",
      "乳腺外科",
      "肛門外科",
      "整形外科",
      "泌尿器科",
      "リウマチ科",
      "リハビリテーション科"
    ]
  },
  {
    "id": "2411240000440",
    "name": "名張市立病院",
    "tel": "2411240000440",
    "url": "http://nabari-city-hospital.jp/",
    "address": "三重県名張市百合が丘西１番町１７８",
    "pref": "三重県",
    "city": "名張市百合が丘西",
    "kind": "hospital",
    "departments": [
      "内科",
      "循環器内科",
      "外科",
      "脳神経外科",
      "整形外科",
      "小児科",
      "眼科",
      "放射線科",
      "麻酔科"
    ]
  },
  {
    "id": "2411240000330",
    "name": "三重県厚生農業協同組合連合会　鈴鹿中央総合病院",
    "tel": "2411240000330",
    "url": "http://www.miekosei.or.jp/2_sch/",
    "address": "三重県鈴鹿市安塚町山之花１２７５－５３",
    "pref": "三重県",
    "city": "鈴鹿市安塚町山之花",
    "kind": "hospital",
    "departments": [
      "内科",
      "血液",
      "腫瘍内科",
      "呼吸器内科",
      "循環器内科",
      "消化器内科",
      "腎臓内科",
      "神経内科",
      "緩和ケア内科",
      "外科",
      "脳神経外科",
      "呼吸器外科",
      "心臓血管外科",
      "消化器外科",
      "整形外科",
      "小児科",
      "産婦人科",
      "眼科",
      "耳鼻いんこう科",
      "皮膚科",
      "泌尿器科",
      "精神科",
      "リウマチ科",
      "リハビリテーション科",
      "放射線科",
      "病理診断科",
      "麻酔科"
    ]
  },
  {
    "id": "2411240000940",
    "name": "独立行政法人　国立病院機構　鈴鹿病院",
    "tel": "2411240000940",
    "url": "https://suzuka.hosp.go.jp/",
    "address": "三重県鈴鹿市加佐登３－２－１",
    "pref": "三重県",
    "city": "鈴鹿市加佐登",
    "kind": "hospital",
    "departments": [
      "内科",
      "循環器内科",
      "神経内科",
      "整形外科",
      "小児科",
      "皮膚科",
      "歯科",
      "リハビリテーション科"
    ]
  },
  {
    "id": "2411240000920",
    "name": "三重県厚生農業協同組合連合会　鈴鹿厚生病院",
    "tel": "2411240000920",
    "url": "http://www.miekosei.or.jp/7_skh/",
    "address": "三重県鈴鹿市岸岡町５８９－２",
    "pref": "三重県",
    "city": "鈴鹿市岸岡町",
    "kind": "hospital",
    "departments": [
      "精神科"
    ]
  },
  {
    "id": "2411240000370",
    "name": "高木病院",
    "tel": "2411240000370",
    "url": "http://takagihp.jp/",
    "address": "三重県鈴鹿市高岡町５５０",
    "pref": "三重県",
    "city": "鈴鹿市高岡町",
    "kind": "hospital",
    "departments": [
      "内科",
      "消化器内科",
      "外科",
      "肛門外科",
      "皮膚科",
      "リハビリテーション科"
    ]
  },
  {
    "id": "2411240000140",
    "name": "社会医療法人　峰和会　鈴鹿回生病院",
    "tel": "2411240000140",
    "url": "http://www.kaiseihp.com",
    "address": "三重県鈴鹿市国府町１１２番地１",
    "pref": "三重県",
    "city": "鈴鹿市国府町",
    "kind": "hospital",
    "departments": [
      "内科",
      "血液内科",
      "循環器内科",
      "消化器内科",
      "腎臓内科",
      "神経内科",
      "外科",
      "脳神経外科",
      "呼吸器外科",
      "心臓血管外科",
      "消化器外科",
      "整形外科",
      "小児科",
      "婦人科",
      "眼科",
      "耳鼻いんこう科",
      "泌尿器科",
      "精神科",
      "リハビリテーション科",
      "放射線科",
      "麻酔科"
    ]
  },
  {
    "id": "2411240000560",
    "name": "村瀬病院",
    "tel": "2411240000560",
    "url": "https://www.murase.or.jp",
    "address": "三重県鈴鹿市神戸３－１２－１０",
    "pref": "三重県",
    "city": "鈴鹿市神戸",
    "kind": "hospital",
    "departments": [
      "内科",
      "糖尿病内科",
      "脳神経内科",
      "呼吸器内科",
      "循環器内科",
      "消化器内科",
      "腎臓内科",
      "ペインクリニック内科",
      "外科",
      "整形外科",
      "皮膚科",
      "泌尿器科",
      "リハビリテーション科",
      "放射線科",
      "麻酔科"
    ]
  },
  {
    "id": "2411240001260",
    "name": "鈴鹿さくら病院",
    "tel": "2411240001260",
    "url": "http://www.mecha.ne.jp/~h-sakura",
    "address": "三重県鈴鹿市中冨田町中谷５１８",
    "pref": "三重県",
    "city": "鈴鹿市中冨田町中谷",
    "kind": "hospital",
    "departments": [
      "内科",
      "精神科"
    ]
  },
  {
    "id": "2411249000008",
    "name": "鈴鹿医療科学大学附属桜の森病院",
    "tel": "2411249000008",
    "url": "https://www.suzuka-u.ac.jp/facilities/kanwa_hosp/",
    "address": "三重県鈴鹿市南玉垣町７３００番地１",
    "pref": "三重県",
    "city": "鈴鹿市南玉垣町",
    "kind": "hospital",
    "departments": [
      "緩和ケア内科"
    ]
  },
  {
    "id": "2411249000015",
    "name": "白子ウィメンズホスピタル",
    "tel": "2411249000015",
    "url": "https://www.shiroko-clinic.com",
    "address": "三重県鈴鹿市南江島町９－１５",
    "pref": "三重県",
    "city": "鈴鹿市南江島町",
    "kind": "hospital",
    "departments": [
      "乳腺外科",
      "小児科",
      "産科",
      "婦人科"
    ]
  },
  {
    "id": "2411240000300",
    "name": "医療法人　誠仁会　塩川病院",
    "tel": "2411240000300",
    "url": "http://www.shiokawa-hp.jp",
    "address": "三重県鈴鹿市平田１－３－７",
    "pref": "三重県",
    "city": "鈴鹿市平田",
    "kind": "hospital",
    "departments": [
      "内科",
      "消化器内科",
      "脳神経外科",
      "整形外科",
      "皮膚科"
    ]
  }
]